{
  "exposure_type": "intermediate",
  "analysis_date": "2025-12-19 11:18:26.55288",
  "age_groups": {
    "age_60_69": {
      "n_regions": 127,
      "pooled_mmt": 25.640682,
      "heterogeneity": {
        "cochrans_Q": 128.506048,
        "Q_df": 126,
        "Q_pvalue": 0.42122,
        "I2_percent": 1.95014
      },
      "heat": {
        "rr": 1.230723,
        "ci_low": 1.164115,
        "ci_high": 1.301142,
        "log_rr": 0.207602,
        "se": 0.028388
      },
      "cold": {
        "rr": 1.3753,
        "ci_low": 1.293525,
        "ci_high": 1.462244,
        "log_rr": 0.318672,
        "se": 0.031276
      },
      "converged": true,
      "method": "ml"
    },
    "age_70_79": {
      "n_regions": 127,
      "pooled_mmt": 25.163737,
      "heterogeneity": {
        "cochrans_Q": 158.3129,
        "Q_df": 126,
        "Q_pvalue": 0.027125,
        "I2_percent": 20.410781
      },
      "heat": {
        "rr": 1.417409,
        "ci_low": 1.333436,
        "ci_high": 1.50667,
        "log_rr": 0.34883,
        "se": 0.031159
      },
      "cold": {
        "rr": 1.412205,
        "ci_low": 1.306451,
        "ci_high": 1.52652,
        "log_rr": 0.345152,
        "se": 0.039713
      },
      "converged": true,
      "method": "ml"
    },
    "age_80plus": {
      "n_regions": 127,
      "pooled_mmt": 25.044552,
      "heterogeneity": {
        "cochrans_Q": 161.936989,
        "Q_df": 126,
        "Q_pvalue": 0.017018,
        "I2_percent": 22.191958
      },
      "heat": {
        "rr": 2.041533,
        "ci_low": 1.802136,
        "ci_high": 2.312732,
        "log_rr": 0.713701,
        "se": 0.063637
      },
      "cold": {
        "rr": 1.810345,
        "ci_low": 1.688193,
        "ci_high": 1.941334,
        "log_rr": 0.593517,
        "se": 0.035642
      },
      "converged": true,
      "method": "ml"
    }
  },
  "age_comparison": [
    {
      "age_group": "age_60_69",
      "heat_log_rr": 0.207602,
      "heat_se": 0.028388,
      "cold_log_rr": 0.318672,
      "cold_se": 0.031276,
      "_row": "age_60_69.30.0209122657776"
    },
    {
      "age_group": "age_70_79",
      "heat_log_rr": 0.34883,
      "heat_se": 0.031159,
      "cold_log_rr": 0.345152,
      "cold_se": 0.039713,
      "_row": "age_70_79.30.0711684417725"
    },
    {
      "age_group": "age_80plus",
      "heat_log_rr": 0.713701,
      "heat_se": 0.063637,
      "cold_log_rr": 0.593517,
      "cold_se": 0.035642,
      "_row": "age_80plus.30.1366532897949"
    }
  ]
}
